[
  {
    "kode":"12.18.11",
    "jumlah_desa":9.0,
    "keterangan":"Perubahan nama  Kec. Bangun Purba, Perda No. 6\/2006",
    "level":"kecamatan",
    "nama_bersih":"",
    "parent_provinsi":"",
    "parent_kabupaten":""
  },
  {
    "kode":"12.18.11.2004",
    "jumlah_desa":null,
    "keterangan":"",
    "level":"desa",
    "nama_bersih":"",
    "parent_provinsi":"",
    "parent_kabupaten":""
  },
  {
    "kode":"12.18.11.2013",
    "jumlah_desa":null,
    "keterangan":"",
    "level":"desa",
    "nama_bersih":"",
    "parent_provinsi":"",
    "parent_kabupaten":""
  },
  {
    "kode":"12.18.11.2016",
    "jumlah_desa":null,
    "keterangan":"",
    "level":"desa",
    "nama_bersih":"",
    "parent_provinsi":"",
    "parent_kabupaten":""
  },
  {
    "kode":"12.18.11.2021",
    "jumlah_desa":null,
    "keterangan":"",
    "level":"desa",
    "nama_bersih":"",
    "parent_provinsi":"",
    "parent_kabupaten":""
  },
  {
    "kode":"12.18.11.2022",
    "jumlah_desa":null,
    "keterangan":"",
    "level":"desa",
    "nama_bersih":"",
    "parent_provinsi":"",
    "parent_kabupaten":""
  },
  {
    "kode":"12.18.11.2026",
    "jumlah_desa":null,
    "keterangan":"",
    "level":"desa",
    "nama_bersih":"",
    "parent_provinsi":"",
    "parent_kabupaten":""
  },
  {
    "kode":"12.18.11.2028",
    "jumlah_desa":null,
    "keterangan":"",
    "level":"desa",
    "nama_bersih":"",
    "parent_provinsi":"",
    "parent_kabupaten":""
  },
  {
    "kode":"12.18.11.2029",
    "jumlah_desa":null,
    "keterangan":"",
    "level":"desa",
    "nama_bersih":"",
    "parent_provinsi":"",
    "parent_kabupaten":""
  },
  {
    "kode":"12.18.11.2031",
    "jumlah_desa":null,
    "keterangan":"",
    "level":"desa",
    "nama_bersih":"",
    "parent_provinsi":"",
    "parent_kabupaten":""
  }
]